{
  "video_id": "NXUKBWUILSw",
  "video_title": "Der 11. November um 11_11 Uhr \ud83c\udf89 #karneval #d\u00fcsseldorf #learngerman #shorts",
  "video_link": "https://www.youtube.com/watch?v=NXUKBWUILSw",
  "nouns": [
    [
      {
        "text": "dein",
        "pos": "DET",
        "dep": "nk",
        "morph": {
          "Case": "Acc",
          "Gender": "Neut",
          "Number": "Sing",
          "Poss": "Yes",
          "PronType": "Prs"
        },
        "lemma": "dein",
        "shape": "xxxx",
        "tag": "PPOSAT",
        "lang": "de",
        "prefix": "d",
        "suffix": "ein"
      },
      {
        "text": "Kost\u00fcm",
        "pos": "NOUN",
        "dep": "oa",
        "morph": {
          "Case": "Acc",
          "Gender": "Neut",
          "Number": "Sing"
        },
        "lemma": "Kost\u00fcm",
        "shape": "Xxxxx",
        "tag": "NN",
        "lang": "de",
        "prefix": "K",
        "suffix": "t\u00fcm"
      }
    ],
    [
      {
        "text": "bisschen",
        "pos": "DET",
        "dep": "nk",
        "morph": {
          "PronType": "Ind"
        },
        "lemma": "bisschen",
        "shape": "xxxx",
        "tag": "PIAT",
        "lang": "de",
        "prefix": "b",
        "suffix": "hen"
      },
      {
        "text": "Spa\u00df",
        "pos": "NOUN",
        "dep": "oa",
        "morph": {
          "Case": "Acc",
          "Gender": "Masc",
          "Number": "Sing"
        },
        "lemma": "Spa\u00df",
        "shape": "Xxxx",
        "tag": "NN",
        "lang": "de",
        "prefix": "S",
        "suffix": "pa\u00df"
      }
    ],
    [
      {
        "text": "der",
        "pos": "DET",
        "dep": "nk",
        "morph": {
          "Case": "Nom",
          "Definite": "Def",
          "Gender": "Masc",
          "Number": "Sing",
          "PronType": "Art"
        },
        "lemma": "der",
        "shape": "xxx",
        "tag": "ART",
        "lang": "de",
        "prefix": "d",
        "suffix": "der"
      },
      {
        "text": "B\u00e4r",
        "pos": "NOUN",
        "dep": "pd",
        "morph": {
          "Case": "Nom",
          "Gender": "Masc",
          "Number": "Sing"
        },
        "lemma": "B\u00e4r",
        "shape": "Xxx",
        "tag": "NN",
        "lang": "de",
        "prefix": "B",
        "suffix": "B\u00e4r"
      }
    ],
    [
      {
        "text": "der",
        "pos": "DET",
        "dep": "nk",
        "morph": {
          "Case": "Dat",
          "Definite": "Def",
          "Gender": "Fem",
          "Number": "Sing",
          "PronType": "Art"
        },
        "lemma": "der",
        "shape": "xxx",
        "tag": "ART",
        "lang": "de",
        "prefix": "d",
        "suffix": "der"
      },
      {
        "text": "Suche",
        "pos": "NOUN",
        "dep": "nk",
        "morph": {
          "Case": "Dat",
          "Gender": "Fem",
          "Number": "Sing"
        },
        "lemma": "Suche",
        "shape": "Xxxxx",
        "tag": "NN",
        "lang": "de",
        "prefix": "S",
        "suffix": "che"
      }
    ],
    [
      {
        "text": "ein",
        "pos": "DET",
        "dep": "nk",
        "morph": {
          "Case": "Nom",
          "Definite": "Ind",
          "Gender": "Neut",
          "Number": "Sing",
          "PronType": "Art"
        },
        "lemma": "ein",
        "shape": "xxx",
        "tag": "ART",
        "lang": "de",
        "prefix": "e",
        "suffix": "ein"
      },
      {
        "text": "Reh",
        "pos": "NOUN",
        "dep": "pd",
        "morph": {
          "Case": "Nom",
          "Gender": "Neut",
          "Number": "Sing"
        },
        "lemma": "Reh",
        "shape": "Xxx",
        "tag": "NN",
        "lang": "de",
        "prefix": "R",
        "suffix": "Reh"
      }
    ],
    [
      {
        "text": "Oder",
        "pos": "CCONJ",
        "dep": "ju",
        "morph": {},
        "lemma": "oder",
        "shape": "Xxxx",
        "tag": "KON",
        "lang": "de",
        "prefix": "O",
        "suffix": "der"
      },
      {
        "text": "eine",
        "pos": "DET",
        "dep": "nk",
        "morph": {
          "Case": "Nom",
          "Definite": "Ind",
          "Gender": "Fem",
          "Number": "Sing",
          "PronType": "Art"
        },
        "lemma": "ein",
        "shape": "xxxx",
        "tag": "ART",
        "lang": "de",
        "prefix": "e",
        "suffix": "ine"
      },
      {
        "text": "Ziege",
        "pos": "NOUN",
        "dep": "ROOT",
        "morph": {
          "Case": "Nom",
          "Gender": "Fem",
          "Number": "Sing"
        },
        "lemma": "Ziege",
        "shape": "Xxxxx",
        "tag": "NN",
        "lang": "de",
        "prefix": "Z",
        "suffix": "ege"
      }
    ],
    [
      {
        "text": "eine",
        "pos": "DET",
        "dep": "nk",
        "morph": {
          "Case": "Nom",
          "Definite": "Ind",
          "Gender": "Fem",
          "Number": "Sing",
          "PronType": "Art"
        },
        "lemma": "ein",
        "shape": "xxxx",
        "tag": "ART",
        "lang": "de",
        "prefix": "e",
        "suffix": "ine"
      },
      {
        "text": "Ziege",
        "pos": "NOUN",
        "dep": "re",
        "morph": {
          "Case": "Nom",
          "Gender": "Fem",
          "Number": "Sing"
        },
        "lemma": "Ziege",
        "shape": "Xxxxx",
        "tag": "NN",
        "lang": "de",
        "prefix": "Z",
        "suffix": "ege"
      }
    ],
    [
      {
        "text": "ein",
        "pos": "DET",
        "dep": "nk",
        "morph": {
          "Case": "Nom",
          "Definite": "Ind",
          "Gender": "Neut",
          "Number": "Sing",
          "PronType": "Art"
        },
        "lemma": "ein",
        "shape": "xxx",
        "tag": "ART",
        "lang": "de",
        "prefix": "e",
        "suffix": "ein"
      },
      {
        "text": "Schweinchen",
        "pos": "NOUN",
        "dep": "pd",
        "morph": {
          "Case": "Nom",
          "Gender": "Neut",
          "Number": "Sing"
        },
        "lemma": "Schweinchen",
        "shape": "Xxxxx",
        "tag": "NN",
        "lang": "de",
        "prefix": "S",
        "suffix": "hen"
      }
    ],
    [
      {
        "text": "ein",
        "pos": "DET",
        "dep": "nk",
        "morph": {
          "Case": "Nom",
          "Definite": "Ind",
          "Gender": "Neut",
          "Number": "Sing",
          "PronType": "Art"
        },
        "lemma": "ein",
        "shape": "xxx",
        "tag": "ART",
        "lang": "de",
        "prefix": "e",
        "suffix": "ein"
      },
      {
        "text": "Schweinchen",
        "pos": "NOUN",
        "dep": "pd",
        "morph": {
          "Case": "Nom",
          "Gender": "Neut",
          "Number": "Sing"
        },
        "lemma": "Schweinchen",
        "shape": "Xxxxx",
        "tag": "NN",
        "lang": "de",
        "prefix": "S",
        "suffix": "hen"
      }
    ],
    [
      {
        "text": "die",
        "pos": "DET",
        "dep": "nk",
        "morph": {
          "Case": "Nom",
          "Definite": "Def",
          "Gender": "Masc",
          "Number": "Plur",
          "PronType": "Art"
        },
        "lemma": "der",
        "shape": "xxx",
        "tag": "ART",
        "lang": "de",
        "prefix": "d",
        "suffix": "die"
      },
      {
        "text": "Ahoi-Brause-Kapit\u00e4ne",
        "pos": "NOUN",
        "dep": "pd",
        "morph": {
          "Case": "Nom",
          "Gender": "Masc",
          "Number": "Plur"
        },
        "lemma": "Ahoi-Brause-Kapit\u00e4n",
        "shape": "Xxxx-Xxxxx-Xxxxx",
        "tag": "NN",
        "lang": "de",
        "prefix": "A",
        "suffix": "\u00e4ne"
      }
    ],
    [
      {
        "text": "unsere",
        "pos": "DET",
        "dep": "nk",
        "morph": {
          "Case": "Nom",
          "Gender": "Fem",
          "Number": "Plur",
          "Poss": "Yes",
          "PronType": "Prs"
        },
        "lemma": "unser",
        "shape": "xxxx",
        "tag": "PPOSAT",
        "lang": "de",
        "prefix": "u",
        "suffix": "ere"
      },
      {
        "text": "Frauen",
        "pos": "NOUN",
        "dep": "pd",
        "morph": {
          "Case": "Nom",
          "Gender": "Fem",
          "Number": "Plur"
        },
        "lemma": "Frau",
        "shape": "Xxxxx",
        "tag": "NN",
        "lang": "de",
        "prefix": "F",
        "suffix": "uen"
      }
    ],
    [
      {
        "text": "die",
        "pos": "DET",
        "dep": "nk",
        "morph": {
          "Case": "Nom",
          "Definite": "Def",
          "Gender": "Masc",
          "Number": "Plur",
          "PronType": "Art"
        },
        "lemma": "der",
        "shape": "xxx",
        "tag": "ART",
        "lang": "de",
        "prefix": "d",
        "suffix": "die"
      },
      {
        "text": "Panzerknacker",
        "pos": "NOUN",
        "dep": "pd",
        "morph": {
          "Case": "Nom",
          "Gender": "Masc",
          "Number": "Plur"
        },
        "lemma": "Panzerknacker",
        "shape": "Xxxxx",
        "tag": "NN",
        "lang": "de",
        "prefix": "P",
        "suffix": "ker"
      }
    ],
    [
      {
        "text": "dem",
        "pos": "DET",
        "dep": "nk",
        "morph": {
          "Case": "Dat",
          "Definite": "Def",
          "Gender": "Masc",
          "Number": "Sing",
          "PronType": "Art"
        },
        "lemma": "der",
        "shape": "xxx",
        "tag": "ART",
        "lang": "de",
        "prefix": "d",
        "suffix": "dem"
      },
      {
        "text": "Knast",
        "pos": "NOUN",
        "dep": "nk",
        "morph": {
          "Case": "Dat",
          "Gender": "Masc",
          "Number": "Sing"
        },
        "lemma": "Knast",
        "shape": "Xxxxx",
        "tag": "NN",
        "lang": "de",
        "prefix": "K",
        "suffix": "ast"
      }
    ],
    [
      {
        "text": "eure",
        "pos": "DET",
        "dep": "nk",
        "morph": {
          "Case": "Acc",
          "Gender": "Neut",
          "Number": "Plur",
          "Poss": "Yes",
          "PronType": "Prs"
        },
        "lemma": "euer",
        "shape": "xxxx",
        "tag": "PPOSAT",
        "lang": "de",
        "prefix": "e",
        "suffix": "ure"
      },
      {
        "text": "Kost\u00fcme",
        "pos": "NOUN",
        "dep": "oa",
        "morph": {
          "Case": "Acc",
          "Gender": "Neut",
          "Number": "Plur"
        },
        "lemma": "Kost\u00fcm",
        "shape": "Xxxxx",
        "tag": "NN",
        "lang": "de",
        "prefix": "K",
        "suffix": "\u00fcme"
      }
    ],
    [
      {
        "text": "ein",
        "pos": "DET",
        "dep": "nk",
        "morph": {
          "Case": "Nom",
          "Definite": "Ind",
          "Gender": "Neut",
          "Number": "Sing",
          "PronType": "Art"
        },
        "lemma": "ein",
        "shape": "xxx",
        "tag": "ART",
        "lang": "de",
        "prefix": "e",
        "suffix": "ein"
      },
      {
        "text": "geiles",
        "pos": "ADJ",
        "dep": "nk",
        "morph": {
          "Case": "Nom",
          "Degree": "Pos",
          "Gender": "Neut",
          "Number": "Sing"
        },
        "lemma": "geil",
        "shape": "xxxx",
        "tag": "ADJA",
        "lang": "de",
        "prefix": "g",
        "suffix": "les"
      },
      {
        "text": "Kost\u00fcm",
        "pos": "NOUN",
        "dep": "pd",
        "morph": {
          "Case": "Nom",
          "Gender": "Neut",
          "Number": "Sing"
        },
        "lemma": "Kost\u00fcm",
        "shape": "Xxxxx",
        "tag": "NN",
        "lang": "de",
        "prefix": "K",
        "suffix": "t\u00fcm"
      }
    ],
    [
      {
        "text": "das",
        "pos": "DET",
        "dep": "nk",
        "morph": {
          "Case": "Nom",
          "Definite": "Def",
          "Gender": "Neut",
          "Number": "Sing",
          "PronType": "Art"
        },
        "lemma": "der",
        "shape": "xxx",
        "tag": "ART",
        "lang": "de",
        "prefix": "d",
        "suffix": "das"
      },
      {
        "text": "Kost\u00fcm",
        "pos": "NOUN",
        "dep": "sb",
        "morph": {
          "Case": "Nom",
          "Gender": "Neut",
          "Number": "Sing"
        },
        "lemma": "Kost\u00fcm",
        "shape": "Xxxxx",
        "tag": "NN",
        "lang": "de",
        "prefix": "K",
        "suffix": "t\u00fcm"
      }
    ],
    [
      {
        "text": "also",
        "pos": "ADV",
        "dep": "mo",
        "morph": {},
        "lemma": "also",
        "shape": "xxxx",
        "tag": "ADV",
        "lang": "de",
        "prefix": "a",
        "suffix": "lso"
      },
      {
        "text": "ein",
        "pos": "DET",
        "dep": "nk",
        "morph": {
          "Case": "Nom",
          "Definite": "Ind",
          "Gender": "Masc",
          "Number": "Sing",
          "PronType": "Art"
        },
        "lemma": "ein",
        "shape": "xxx",
        "tag": "ART",
        "lang": "de",
        "prefix": "e",
        "suffix": "ein"
      },
      {
        "text": "versauter",
        "pos": "ADJ",
        "dep": "nk",
        "morph": {
          "Case": "Nom",
          "Degree": "Pos",
          "Gender": "Masc",
          "Number": "Sing"
        },
        "lemma": "versaut",
        "shape": "xxxx",
        "tag": "ADJA",
        "lang": "de",
        "prefix": "v",
        "suffix": "ter"
      },
      {
        "text": "Footballplayer",
        "pos": "NOUN",
        "dep": "dep",
        "morph": {
          "Case": "Nom",
          "Gender": "Masc",
          "Number": "Sing"
        },
        "lemma": "Footballplayer",
        "shape": "Xxxxx",
        "tag": "NN",
        "lang": "de",
        "prefix": "F",
        "suffix": "yer"
      }
    ]
  ]
}