{
  "video_id": "ti3EWgOOFdM",
  "video_title": "M\u00f6chtest du ewig leben\uff1f #shorts #liveforever #ewigesleben #philosophical",
  "video_link": "https://www.youtube.com/watch?v=ti3EWgOOFdM",
  "nouns": [
    [
      {
        "text": "Wie",
        "pos": "ADP",
        "dep": "cm",
        "morph": {},
        "lemma": "wie",
        "shape": "Xxx",
        "tag": "KOKOM",
        "lang": "de",
        "prefix": "W",
        "suffix": "Wie"
      },
      {
        "text": "ein",
        "pos": "DET",
        "dep": "nk",
        "morph": {
          "Case": "Nom",
          "Definite": "Ind",
          "Gender": "Masc",
          "Number": "Sing",
          "PronType": "Art"
        },
        "lemma": "ein",
        "shape": "xxx",
        "tag": "ART",
        "lang": "de",
        "prefix": "e",
        "suffix": "ein"
      },
      {
        "text": "Hexe",
        "pos": "NOUN",
        "dep": "ROOT",
        "morph": {
          "Case": "Nom",
          "Gender": "Fem",
          "Number": "Sing"
        },
        "lemma": "Hexe",
        "shape": "Xxxx",
        "tag": "NN",
        "lang": "de",
        "prefix": "H",
        "suffix": "exe"
      }
    ],
    [
      {
        "text": "jeden",
        "pos": "DET",
        "dep": "nk",
        "morph": {
          "Case": "Acc",
          "Gender": "Masc",
          "Number": "Sing",
          "PronType": "Ind"
        },
        "lemma": "jeder",
        "shape": "xxxx",
        "tag": "PIAT",
        "lang": "de",
        "prefix": "j",
        "suffix": "den"
      },
      {
        "text": "Fall",
        "pos": "NOUN",
        "dep": "nk",
        "morph": {
          "Case": "Acc",
          "Gender": "Masc",
          "Number": "Sing"
        },
        "lemma": "Fall",
        "shape": "Xxxx",
        "tag": "NN",
        "lang": "de",
        "prefix": "F",
        "suffix": "all"
      }
    ],
    [
      {
        "text": "manche",
        "pos": "DET",
        "dep": "nk",
        "morph": {
          "Case": "Nom",
          "Number": "Plur",
          "PronType": "Ind"
        },
        "lemma": "mancher",
        "shape": "xxxx",
        "tag": "PIAT",
        "lang": "de",
        "prefix": "m",
        "suffix": "che"
      },
      {
        "text": "Leute",
        "pos": "NOUN",
        "dep": "sb",
        "morph": {
          "Case": "Nom",
          "Number": "Plur"
        },
        "lemma": "Leute",
        "shape": "Xxxxx",
        "tag": "NN",
        "lang": "de",
        "prefix": "L",
        "suffix": "ute"
      }
    ]
  ]
}