{
  "video_id": "OOZhdiznqks",
  "video_title": "NACH vs. ZU vs. IN \uff5c Super Easy German (89)",
  "video_link": "https://www.youtube.com/watch?v=OOZhdiznqks",
  "nouns": [
    [
      {
        "text": "einer",
        "pos": "DET",
        "dep": "nk",
        "morph": {
          "Case": "Dat",
          "Definite": "Ind",
          "Gender": "Fem",
          "Number": "Sing",
          "PronType": "Art"
        },
        "lemma": "ein",
        "shape": "xxxx",
        "tag": "ART",
        "lang": "de",
        "prefix": "e",
        "suffix": "ner"
      },
      {
        "text": "neuen",
        "pos": "ADJ",
        "dep": "nk",
        "morph": {
          "Case": "Dat",
          "Degree": "Pos",
          "Gender": "Fem",
          "Number": "Sing"
        },
        "lemma": "neu",
        "shape": "xxxx",
        "tag": "ADJA",
        "lang": "de",
        "prefix": "n",
        "suffix": "uen"
      },
      {
        "text": "Episode",
        "pos": "NOUN",
        "dep": "nk",
        "morph": {
          "Case": "Dat",
          "Gender": "Fem",
          "Number": "Sing"
        },
        "lemma": "Episode",
        "shape": "Xxxxx",
        "tag": "NN",
        "lang": "de",
        "prefix": "E",
        "suffix": "ode"
      }
    ],
    [
      {
        "text": "drei",
        "pos": "NUM",
        "dep": "nk",
        "morph": {},
        "lemma": "drei",
        "shape": "xxxx",
        "tag": "CARD",
        "lang": "de",
        "prefix": "d",
        "suffix": "rei"
      },
      {
        "text": "verschiedene",
        "pos": "ADJ",
        "dep": "nk",
        "morph": {
          "Case": "Acc",
          "Degree": "Pos",
          "Gender": "Fem",
          "Number": "Plur"
        },
        "lemma": "verschieden",
        "shape": "xxxx",
        "tag": "ADJA",
        "lang": "de",
        "prefix": "v",
        "suffix": "ene"
      },
      {
        "text": "Pr\u00e4positionen",
        "pos": "NOUN",
        "dep": "oa",
        "morph": {
          "Case": "Acc",
          "Gender": "Fem",
          "Number": "Plur"
        },
        "lemma": "Pr\u00e4position",
        "shape": "Xxxxx",
        "tag": "NN",
        "lang": "de",
        "prefix": "P",
        "suffix": "nen"
      }
    ],
    [
      {
        "text": "drei",
        "pos": "NUM",
        "dep": "nk",
        "morph": {},
        "lemma": "drei",
        "shape": "xxxx",
        "tag": "CARD",
        "lang": "de",
        "prefix": "d",
        "suffix": "rei"
      },
      {
        "text": "verschiedene",
        "pos": "ADJ",
        "dep": "nk",
        "morph": {
          "Case": "Acc",
          "Degree": "Pos",
          "Gender": "Fem",
          "Number": "Plur"
        },
        "lemma": "verschieden",
        "shape": "xxxx",
        "tag": "ADJA",
        "lang": "de",
        "prefix": "v",
        "suffix": "ene"
      },
      {
        "text": "Pr\u00e4positionen",
        "pos": "NOUN",
        "dep": "oa",
        "morph": {
          "Case": "Acc",
          "Gender": "Fem",
          "Number": "Plur"
        },
        "lemma": "Pr\u00e4position",
        "shape": "Xxxxx",
        "tag": "NN",
        "lang": "de",
        "prefix": "P",
        "suffix": "nen"
      }
    ],
    [
      {
        "text": "welche",
        "pos": "DET",
        "dep": "nk",
        "morph": {
          "Case": "Acc",
          "Gender": "Fem",
          "Number": "Sing",
          "PronType": "Int"
        },
        "lemma": "welcher",
        "shape": "xxxx",
        "tag": "PWAT",
        "lang": "de",
        "prefix": "w",
        "suffix": "che"
      },
      {
        "text": "Pr\u00e4position",
        "pos": "NOUN",
        "dep": "oa",
        "morph": {
          "Case": "Acc",
          "Gender": "Fem",
          "Number": "Sing"
        },
        "lemma": "Pr\u00e4position",
        "shape": "Xxxxx",
        "tag": "NN",
        "lang": "de",
        "prefix": "P",
        "suffix": "ion"
      }
    ],
    [
      {
        "text": "einen",
        "pos": "DET",
        "dep": "nk",
        "morph": {
          "Case": "Acc",
          "Definite": "Ind",
          "Gender": "Masc",
          "Number": "Sing",
          "PronType": "Art"
        },
        "lemma": "ein",
        "shape": "xxxx",
        "tag": "ART",
        "lang": "de",
        "prefix": "e",
        "suffix": "nen"
      },
      {
        "text": "geschlossenen",
        "pos": "ADJ",
        "dep": "nk",
        "morph": {
          "Case": "Acc",
          "Degree": "Pos",
          "Gender": "Masc",
          "Number": "Sing"
        },
        "lemma": "geschlossen",
        "shape": "xxxx",
        "tag": "ADJA",
        "lang": "de",
        "prefix": "g",
        "suffix": "nen"
      },
      {
        "text": "oder",
        "pos": "CCONJ",
        "dep": "cd",
        "morph": {},
        "lemma": "oder",
        "shape": "xxxx",
        "tag": "KON",
        "lang": "de",
        "prefix": "o",
        "suffix": "der"
      },
      {
        "text": "begrenzten",
        "pos": "ADJ",
        "dep": "cj",
        "morph": {
          "Case": "Acc",
          "Degree": "Pos",
          "Gender": "Masc",
          "Number": "Sing"
        },
        "lemma": "begrenzt",
        "shape": "xxxx",
        "tag": "ADJA",
        "lang": "de",
        "prefix": "b",
        "suffix": "ten"
      },
      {
        "text": "Raum",
        "pos": "NOUN",
        "dep": "nk",
        "morph": {
          "Case": "Acc",
          "Gender": "Masc",
          "Number": "Sing"
        },
        "lemma": "Raum",
        "shape": "Xxxx",
        "tag": "NN",
        "lang": "de",
        "prefix": "R",
        "suffix": "aum"
      }
    ],
    [
      {
        "text": "das",
        "pos": "DET",
        "dep": "nk",
        "morph": {
          "Case": "Acc",
          "Definite": "Def",
          "Gender": "Neut",
          "Number": "Sing",
          "PronType": "Art"
        },
        "lemma": "der",
        "shape": "xxx",
        "tag": "ART",
        "lang": "de",
        "prefix": "d",
        "suffix": "das"
      },
      {
        "text": "Haus",
        "pos": "NOUN",
        "dep": "nk",
        "morph": {
          "Case": "Acc",
          "Gender": "Neut",
          "Number": "Sing"
        },
        "lemma": "Haus",
        "shape": "Xxxx",
        "tag": "NN",
        "lang": "de",
        "prefix": "H",
        "suffix": "aus"
      }
    ],
    [
      {
        "text": "das",
        "pos": "DET",
        "dep": "nk",
        "morph": {
          "Case": "Acc",
          "Definite": "Def",
          "Gender": "Neut",
          "Number": "Sing",
          "PronType": "Art"
        },
        "lemma": "der",
        "shape": "xxx",
        "tag": "ART",
        "lang": "de",
        "prefix": "d",
        "suffix": "das"
      },
      {
        "text": "Geb\u00e4ude",
        "pos": "NOUN",
        "dep": "nk",
        "morph": {
          "Case": "Acc",
          "Gender": "Neut",
          "Number": "Sing"
        },
        "lemma": "Geb\u00e4ude",
        "shape": "Xxxxx",
        "tag": "NN",
        "lang": "de",
        "prefix": "G",
        "suffix": "ude"
      }
    ],
    [
      {
        "text": "ein",
        "pos": "DET",
        "dep": "nk",
        "morph": {
          "Case": "Acc",
          "Definite": "Ind",
          "Gender": "Neut",
          "Number": "Sing",
          "PronType": "Art"
        },
        "lemma": "ein",
        "shape": "xxx",
        "tag": "ART",
        "lang": "de",
        "prefix": "e",
        "suffix": "ein"
      },
      {
        "text": "Dach",
        "pos": "NOUN",
        "dep": "oa",
        "morph": {
          "Case": "Acc",
          "Gender": "Neut",
          "Number": "Sing"
        },
        "lemma": "Dach",
        "shape": "Xxxx",
        "tag": "NN",
        "lang": "de",
        "prefix": "D",
        "suffix": "ach"
      }
    ],
    [
      {
        "text": "eine",
        "pos": "DET",
        "dep": "nk",
        "morph": {
          "Case": "Acc",
          "Definite": "Ind",
          "Gender": "Fem",
          "Number": "Sing",
          "PronType": "Art"
        },
        "lemma": "ein",
        "shape": "xxxx",
        "tag": "ART",
        "lang": "de",
        "prefix": "e",
        "suffix": "ine"
      },
      {
        "text": "Art",
        "pos": "NOUN",
        "dep": "oa",
        "morph": {
          "Case": "Acc",
          "Gender": "Fem",
          "Number": "Sing"
        },
        "lemma": "Art",
        "shape": "Xxx",
        "tag": "NN",
        "lang": "de",
        "prefix": "A",
        "suffix": "Art"
      }
    ],
    [
      {
        "text": "den",
        "pos": "DET",
        "dep": "nk",
        "morph": {
          "Case": "Acc",
          "Definite": "Def",
          "Gender": "Masc",
          "Number": "Sing",
          "PronType": "Art"
        },
        "lemma": "der",
        "shape": "xxx",
        "tag": "ART",
        "lang": "de",
        "prefix": "d",
        "suffix": "den"
      },
      {
        "text": "Park",
        "pos": "NOUN",
        "dep": "nk",
        "morph": {
          "Case": "Acc",
          "Gender": "Masc",
          "Number": "Sing"
        },
        "lemma": "Park",
        "shape": "Xxxx",
        "tag": "NN",
        "lang": "de",
        "prefix": "P",
        "suffix": "ark"
      }
    ],
    [
      {
        "text": "ein",
        "pos": "DET",
        "dep": "nk",
        "morph": {
          "Case": "Nom",
          "Definite": "Ind",
          "Gender": "Masc",
          "Number": "Sing",
          "PronType": "Art"
        },
        "lemma": "ein",
        "shape": "xxx",
        "tag": "ART",
        "lang": "de",
        "prefix": "e",
        "suffix": "ein"
      },
      {
        "text": "geschlossener",
        "pos": "ADJ",
        "dep": "nk",
        "morph": {
          "Case": "Nom",
          "Degree": "Pos",
          "Gender": "Masc",
          "Number": "Sing"
        },
        "lemma": "geschlossen",
        "shape": "xxxx",
        "tag": "ADJA",
        "lang": "de",
        "prefix": "g",
        "suffix": "ner"
      },
      {
        "text": "oder",
        "pos": "CCONJ",
        "dep": "cd",
        "morph": {},
        "lemma": "oder",
        "shape": "xxxx",
        "tag": "KON",
        "lang": "de",
        "prefix": "o",
        "suffix": "der"
      },
      {
        "text": "begrenzter",
        "pos": "ADJ",
        "dep": "cj",
        "morph": {
          "Case": "Nom",
          "Degree": "Pos",
          "Gender": "Masc",
          "Number": "Sing"
        },
        "lemma": "begrenzt",
        "shape": "xxxx",
        "tag": "ADJA",
        "lang": "de",
        "prefix": "b",
        "suffix": "ter"
      },
      {
        "text": "Raum",
        "pos": "NOUN",
        "dep": "pd",
        "morph": {
          "Case": "Nom",
          "Gender": "Masc",
          "Number": "Sing"
        },
        "lemma": "Raum",
        "shape": "Xxxx",
        "tag": "NN",
        "lang": "de",
        "prefix": "R",
        "suffix": "aum"
      }
    ],
    [
      {
        "text": "einer",
        "pos": "DET",
        "dep": "nk",
        "morph": {
          "Case": "Dat",
          "Definite": "Ind",
          "Gender": "Fem",
          "Number": "Sing",
          "PronType": "Art"
        },
        "lemma": "ein",
        "shape": "xxxx",
        "tag": "ART",
        "lang": "de",
        "prefix": "e",
        "suffix": "ner"
      },
      {
        "text": "Person",
        "pos": "NOUN",
        "dep": "nk",
        "morph": {
          "Case": "Dat",
          "Gender": "Fem",
          "Number": "Sing"
        },
        "lemma": "Person",
        "shape": "Xxxxx",
        "tag": "NN",
        "lang": "de",
        "prefix": "P",
        "suffix": "son"
      }
    ],
    [
      {
        "text": "einer",
        "pos": "DET",
        "dep": "nk",
        "morph": {
          "Case": "Dat",
          "Definite": "Ind",
          "Gender": "Fem",
          "Number": "Sing",
          "PronType": "Art"
        },
        "lemma": "ein",
        "shape": "xxxx",
        "tag": "ART",
        "lang": "de",
        "prefix": "e",
        "suffix": "ner"
      },
      {
        "text": "Veranstaltung",
        "pos": "NOUN",
        "dep": "cj",
        "morph": {
          "Case": "Dat",
          "Gender": "Fem",
          "Number": "Sing"
        },
        "lemma": "Veranstaltung",
        "shape": "Xxxxx",
        "tag": "NN",
        "lang": "de",
        "prefix": "V",
        "suffix": "ung"
      }
    ],
    [
      {
        "text": "einer",
        "pos": "DET",
        "dep": "nk",
        "morph": {
          "Case": "Dat",
          "Definite": "Ind",
          "Gender": "Fem",
          "Number": "Sing",
          "PronType": "Art"
        },
        "lemma": "ein",
        "shape": "xxxx",
        "tag": "ART",
        "lang": "de",
        "prefix": "e",
        "suffix": "ner"
      },
      {
        "text": "Institution",
        "pos": "NOUN",
        "dep": "cj",
        "morph": {
          "Case": "Dat",
          "Gender": "Fem",
          "Number": "Sing"
        },
        "lemma": "Institution",
        "shape": "Xxxxx",
        "tag": "NN",
        "lang": "de",
        "prefix": "I",
        "suffix": "ion"
      }
    ],
    [
      {
        "text": "zwei",
        "pos": "NUM",
        "dep": "nk",
        "morph": {},
        "lemma": "zwei",
        "shape": "xxxx",
        "tag": "CARD",
        "lang": "de",
        "prefix": "z",
        "suffix": "wei"
      },
      {
        "text": "Ausnahmen",
        "pos": "NOUN",
        "dep": "oa",
        "morph": {
          "Case": "Acc",
          "Gender": "Fem",
          "Number": "Plur"
        },
        "lemma": "Ausnahme",
        "shape": "Xxxxx",
        "tag": "NN",
        "lang": "de",
        "prefix": "A",
        "suffix": "men"
      }
    ],
    [
      {
        "text": "ein",
        "pos": "DET",
        "dep": "nk",
        "morph": {
          "Case": "Nom",
          "Definite": "Ind",
          "Gender": "Masc",
          "Number": "Sing",
          "PronType": "Art"
        },
        "lemma": "ein",
        "shape": "xxx",
        "tag": "ART",
        "lang": "de",
        "prefix": "e",
        "suffix": "ein"
      },
      {
        "text": "fester",
        "pos": "ADJ",
        "dep": "nk",
        "morph": {
          "Case": "Nom",
          "Degree": "Pos",
          "Gender": "Masc",
          "Number": "Sing"
        },
        "lemma": "fest",
        "shape": "xxxx",
        "tag": "ADJA",
        "lang": "de",
        "prefix": "f",
        "suffix": "ter"
      },
      {
        "text": "Ausdruck",
        "pos": "NOUN",
        "dep": "pd",
        "morph": {
          "Case": "Nom",
          "Gender": "Masc",
          "Number": "Sing"
        },
        "lemma": "Ausdruck",
        "shape": "Xxxxx",
        "tag": "NN",
        "lang": "de",
        "prefix": "A",
        "suffix": "uck"
      }
    ],
    [
      {
        "text": "ein",
        "pos": "DET",
        "dep": "nk",
        "morph": {
          "Case": "Nom",
          "Definite": "Ind",
          "Gender": "Neut",
          "Number": "Sing",
          "PronType": "Art"
        },
        "lemma": "ein",
        "shape": "xxx",
        "tag": "ART",
        "lang": "de",
        "prefix": "e",
        "suffix": "ein"
      },
      {
        "text": "Land",
        "pos": "NOUN",
        "dep": "sb",
        "morph": {
          "Case": "Nom",
          "Gender": "Neut",
          "Number": "Sing"
        },
        "lemma": "Land",
        "shape": "Xxxx",
        "tag": "NN",
        "lang": "de",
        "prefix": "L",
        "suffix": "and"
      }
    ],
    [
      {
        "text": "einen",
        "pos": "DET",
        "dep": "nk",
        "morph": {
          "Case": "Acc",
          "Definite": "Ind",
          "Gender": "Masc",
          "Number": "Sing",
          "PronType": "Art"
        },
        "lemma": "ein",
        "shape": "xxxx",
        "tag": "ART",
        "lang": "de",
        "prefix": "e",
        "suffix": "nen"
      },
      {
        "text": "Artikel",
        "pos": "NOUN",
        "dep": "oa",
        "morph": {
          "Case": "Acc",
          "Gender": "Masc",
          "Number": "Sing"
        },
        "lemma": "Artikel",
        "shape": "Xxxxx",
        "tag": "NN",
        "lang": "de",
        "prefix": "A",
        "suffix": "kel"
      }
    ],
    [
      {
        "text": "den",
        "pos": "DET",
        "dep": "nk",
        "morph": {
          "Case": "Acc",
          "Definite": "Def",
          "Gender": "Masc",
          "Number": "Sing",
          "PronType": "Art"
        },
        "lemma": "der",
        "shape": "xxx",
        "tag": "ART",
        "lang": "de",
        "prefix": "d",
        "suffix": "den"
      },
      {
        "text": "Jemen",
        "pos": "NOUN",
        "dep": "nk",
        "morph": {
          "Case": "Acc",
          "Gender": "Masc",
          "Number": "Sing"
        },
        "lemma": "Jemen",
        "shape": "Xxxxx",
        "tag": "NN",
        "lang": "de",
        "prefix": "J",
        "suffix": "men"
      }
    ],
    [
      {
        "text": "ein",
        "pos": "DET",
        "dep": "nk",
        "morph": {
          "Case": "Nom",
          "Definite": "Ind",
          "Gender": "Neut",
          "Number": "Sing",
          "PronType": "Art"
        },
        "lemma": "ein",
        "shape": "xxx",
        "tag": "ART",
        "lang": "de",
        "prefix": "e",
        "suffix": "ein"
      },
      {
        "text": "Land",
        "pos": "NOUN",
        "dep": "sb",
        "morph": {
          "Case": "Nom",
          "Gender": "Neut",
          "Number": "Sing"
        },
        "lemma": "Land",
        "shape": "Xxxx",
        "tag": "NN",
        "lang": "de",
        "prefix": "L",
        "suffix": "and"
      }
    ],
    [
      {
        "text": "einen",
        "pos": "DET",
        "dep": "nk",
        "morph": {
          "Case": "Acc",
          "Definite": "Ind",
          "Gender": "Masc",
          "Number": "Sing",
          "PronType": "Art"
        },
        "lemma": "ein",
        "shape": "xxxx",
        "tag": "ART",
        "lang": "de",
        "prefix": "e",
        "suffix": "nen"
      },
      {
        "text": "Artikel",
        "pos": "NOUN",
        "dep": "oa",
        "morph": {
          "Case": "Acc",
          "Gender": "Masc",
          "Number": "Sing"
        },
        "lemma": "Artikel",
        "shape": "Xxxxx",
        "tag": "NN",
        "lang": "de",
        "prefix": "A",
        "suffix": "kel"
      }
    ],
    [
      {
        "text": "eine",
        "pos": "DET",
        "dep": "nk",
        "morph": {
          "Case": "Nom",
          "Definite": "Ind",
          "Gender": "Fem",
          "Number": "Sing",
          "PronType": "Art"
        },
        "lemma": "ein",
        "shape": "xxxx",
        "tag": "ART",
        "lang": "de",
        "prefix": "e",
        "suffix": "ine"
      },
      {
        "text": "Ausnahme",
        "pos": "NOUN",
        "dep": "pd",
        "morph": {
          "Case": "Nom",
          "Gender": "Fem",
          "Number": "Sing"
        },
        "lemma": "Ausnahme",
        "shape": "Xxxxx",
        "tag": "NN",
        "lang": "de",
        "prefix": "A",
        "suffix": "hme"
      }
    ],
    [
      {
        "text": "welche",
        "pos": "DET",
        "dep": "nk",
        "morph": {
          "Case": "Nom",
          "Gender": "Neut",
          "Number": "Plur",
          "PronType": "Int"
        },
        "lemma": "welcher",
        "shape": "xxxx",
        "tag": "PWAT",
        "lang": "de",
        "prefix": "w",
        "suffix": "che"
      },
      {
        "text": "L\u00e4nder",
        "pos": "NOUN",
        "dep": "sb",
        "morph": {
          "Case": "Nom",
          "Gender": "Neut",
          "Number": "Plur"
        },
        "lemma": "Land",
        "shape": "Xxxxx",
        "tag": "NN",
        "lang": "de",
        "prefix": "L",
        "suffix": "der"
      }
    ],
    [
      {
        "text": "einen",
        "pos": "DET",
        "dep": "nk",
        "morph": {
          "Case": "Acc",
          "Definite": "Ind",
          "Gender": "Masc",
          "Number": "Sing",
          "PronType": "Art"
        },
        "lemma": "ein",
        "shape": "xxxx",
        "tag": "ART",
        "lang": "de",
        "prefix": "e",
        "suffix": "nen"
      },
      {
        "text": "Artikel",
        "pos": "NOUN",
        "dep": "oa",
        "morph": {
          "Case": "Acc",
          "Gender": "Masc",
          "Number": "Sing"
        },
        "lemma": "Artikel",
        "shape": "Xxxxx",
        "tag": "NN",
        "lang": "de",
        "prefix": "A",
        "suffix": "kel"
      }
    ],
    [
      {
        "text": "dieses",
        "pos": "DET",
        "dep": "nk",
        "morph": {
          "Case": "Acc",
          "Gender": "Neut",
          "Number": "Sing",
          "PronType": "Dem"
        },
        "lemma": "dieser",
        "shape": "xxxx",
        "tag": "PDAT",
        "lang": "de",
        "prefix": "d",
        "suffix": "ses"
      },
      {
        "text": "Video",
        "pos": "NOUN",
        "dep": "oa",
        "morph": {
          "Case": "Acc",
          "Gender": "Neut",
          "Number": "Sing"
        },
        "lemma": "Video",
        "shape": "Xxxxx",
        "tag": "NN",
        "lang": "de",
        "prefix": "V",
        "suffix": "deo"
      }
    ],
    [
      {
        "text": "manchen",
        "pos": "DET",
        "dep": "nk",
        "morph": {
          "Case": "Dat",
          "Gender": "Masc",
          "Number": "Plur",
          "PronType": "Ind"
        },
        "lemma": "mancher",
        "shape": "xxxx",
        "tag": "PIAT",
        "lang": "de",
        "prefix": "m",
        "suffix": "hen"
      },
      {
        "text": "Orten",
        "pos": "NOUN",
        "dep": "nk",
        "morph": {
          "Case": "Dat",
          "Gender": "Masc",
          "Number": "Plur"
        },
        "lemma": "Ort",
        "shape": "Xxxxx",
        "tag": "NN",
        "lang": "de",
        "prefix": "O",
        "suffix": "ten"
      }
    ],
    [
      {
        "text": "zwei",
        "pos": "NUM",
        "dep": "nk",
        "morph": {},
        "lemma": "zwei",
        "shape": "xxxx",
        "tag": "CARD",
        "lang": "de",
        "prefix": "z",
        "suffix": "wei"
      },
      {
        "text": "Pr\u00e4positionen",
        "pos": "NOUN",
        "dep": "oa",
        "morph": {
          "Case": "Acc",
          "Gender": "Fem",
          "Number": "Plur"
        },
        "lemma": "Pr\u00e4position",
        "shape": "Xxxxx",
        "tag": "NN",
        "lang": "de",
        "prefix": "P",
        "suffix": "nen"
      }
    ],
    [
      {
        "text": "die",
        "pos": "DET",
        "dep": "nk",
        "morph": {
          "Case": "Acc",
          "Definite": "Def",
          "Gender": "Fem",
          "Number": "Sing",
          "PronType": "Art"
        },
        "lemma": "der",
        "shape": "xxx",
        "tag": "ART",
        "lang": "de",
        "prefix": "d",
        "suffix": "die"
      },
      {
        "text": "Schule",
        "pos": "NOUN",
        "dep": "nk",
        "morph": {
          "Case": "Acc",
          "Gender": "Fem",
          "Number": "Sing"
        },
        "lemma": "Schule",
        "shape": "Xxxxx",
        "tag": "NN",
        "lang": "de",
        "prefix": "S",
        "suffix": "ule"
      }
    ],
    [
      {
        "text": "ein",
        "pos": "DET",
        "dep": "nk",
        "morph": {
          "Case": "Nom",
          "Definite": "Ind",
          "Gender": "Neut",
          "Number": "Sing",
          "PronType": "Art"
        },
        "lemma": "ein",
        "shape": "xxx",
        "tag": "ART",
        "lang": "de",
        "prefix": "e",
        "suffix": "ein"
      },
      {
        "text": "geschlossenes",
        "pos": "ADJ",
        "dep": "nk",
        "morph": {
          "Case": "Nom",
          "Degree": "Pos",
          "Gender": "Neut",
          "Number": "Sing"
        },
        "lemma": "geschlossen",
        "shape": "xxxx",
        "tag": "ADJA",
        "lang": "de",
        "prefix": "g",
        "suffix": "nes"
      },
      {
        "text": "Geb\u00e4ude",
        "pos": "NOUN",
        "dep": "pd",
        "morph": {
          "Case": "Nom",
          "Gender": "Neut",
          "Number": "Sing"
        },
        "lemma": "Geb\u00e4ude",
        "shape": "Xxxxx",
        "tag": "NN",
        "lang": "de",
        "prefix": "G",
        "suffix": "ude"
      }
    ],
    [
      {
        "text": "auch",
        "pos": "ADV",
        "dep": "mo",
        "morph": {},
        "lemma": "auch",
        "shape": "xxxx",
        "tag": "ADV",
        "lang": "de",
        "prefix": "a",
        "suffix": "uch"
      },
      {
        "text": "eine",
        "pos": "DET",
        "dep": "nk",
        "morph": {
          "Case": "Nom",
          "Definite": "Ind",
          "Gender": "Fem",
          "Number": "Sing",
          "PronType": "Art"
        },
        "lemma": "ein",
        "shape": "xxxx",
        "tag": "ART",
        "lang": "de",
        "prefix": "e",
        "suffix": "ine"
      },
      {
        "text": "Institution",
        "pos": "NOUN",
        "dep": "pd",
        "morph": {
          "Case": "Nom",
          "Gender": "Fem",
          "Number": "Sing"
        },
        "lemma": "Institution",
        "shape": "Xxxxx",
        "tag": "NN",
        "lang": "de",
        "prefix": "I",
        "suffix": "ion"
      }
    ],
    [
      {
        "text": "eine",
        "pos": "DET",
        "dep": "nk",
        "morph": {
          "Case": "Acc",
          "Definite": "Ind",
          "Gender": "Fem",
          "Number": "Sing",
          "PronType": "Art"
        },
        "lemma": "ein",
        "shape": "xxxx",
        "tag": "ART",
        "lang": "de",
        "prefix": "e",
        "suffix": "ine"
      },
      {
        "text": "kleine",
        "pos": "ADJ",
        "dep": "nk",
        "morph": {
          "Case": "Acc",
          "Degree": "Pos",
          "Gender": "Fem",
          "Number": "Sing"
        },
        "lemma": "klein",
        "shape": "xxxx",
        "tag": "ADJA",
        "lang": "de",
        "prefix": "k",
        "suffix": "ine"
      },
      {
        "text": "Geschichte",
        "pos": "NOUN",
        "dep": "oa",
        "morph": {
          "Case": "Acc",
          "Gender": "Fem",
          "Number": "Sing"
        },
        "lemma": "Geschichte",
        "shape": "Xxxxx",
        "tag": "NN",
        "lang": "de",
        "prefix": "G",
        "suffix": "hte"
      }
    ],
    [
      {
        "text": "mehr",
        "pos": "DET",
        "dep": "nk",
        "morph": {
          "PronType": "Ind"
        },
        "lemma": "mehr",
        "shape": "xxxx",
        "tag": "PIAT",
        "lang": "de",
        "prefix": "m",
        "suffix": "ehr"
      },
      {
        "text": "\u00dcbung",
        "pos": "NOUN",
        "dep": "oa",
        "morph": {
          "Case": "Acc",
          "Gender": "Fem",
          "Number": "Sing"
        },
        "lemma": "\u00dcbung",
        "shape": "Xxxxx",
        "tag": "NN",
        "lang": "de",
        "prefix": "\u00dc",
        "suffix": "ung"
      }
    ],
    [
      {
        "text": "ein",
        "pos": "DET",
        "dep": "nk",
        "morph": {
          "Case": "Acc",
          "Definite": "Ind",
          "Gender": "Neut",
          "Number": "Sing",
          "PronType": "Art"
        },
        "lemma": "ein",
        "shape": "xxx",
        "tag": "ART",
        "lang": "de",
        "prefix": "e",
        "suffix": "ein"
      },
      {
        "text": "Video",
        "pos": "NOUN",
        "dep": "oa",
        "morph": {
          "Case": "Acc",
          "Gender": "Neut",
          "Number": "Sing"
        },
        "lemma": "Video",
        "shape": "Xxxxx",
        "tag": "NN",
        "lang": "de",
        "prefix": "V",
        "suffix": "deo"
      }
    ],
    [
      {
        "text": "einige",
        "pos": "DET",
        "dep": "nk",
        "morph": {
          "Case": "Acc",
          "Gender": "Fem",
          "Number": "Plur",
          "PronType": "Ind"
        },
        "lemma": "einiger",
        "shape": "xxxx",
        "tag": "PIAT",
        "lang": "de",
        "prefix": "e",
        "suffix": "ige"
      },
      {
        "text": "Turbulenzen",
        "pos": "NOUN",
        "dep": "oa",
        "morph": {
          "Case": "Acc",
          "Gender": "Fem",
          "Number": "Plur"
        },
        "lemma": "Turbulenz",
        "shape": "Xxxxx",
        "tag": "NN",
        "lang": "de",
        "prefix": "T",
        "suffix": "zen"
      }
    ],
    [
      {
        "text": "welche",
        "pos": "DET",
        "dep": "nk",
        "morph": {
          "Case": "Acc",
          "Gender": "Fem",
          "Number": "Sing",
          "PronType": "Int"
        },
        "lemma": "welcher",
        "shape": "xxxx",
        "tag": "PWAT",
        "lang": "de",
        "prefix": "w",
        "suffix": "che"
      },
      {
        "text": "Pr\u00e4position",
        "pos": "NOUN",
        "dep": "oa",
        "morph": {
          "Case": "Acc",
          "Gender": "Fem",
          "Number": "Sing"
        },
        "lemma": "Pr\u00e4position",
        "shape": "Xxxxx",
        "tag": "NN",
        "lang": "de",
        "prefix": "P",
        "suffix": "ion"
      }
    ],
    [
      {
        "text": "die",
        "pos": "DET",
        "dep": "nk",
        "morph": {
          "Case": "Nom",
          "Definite": "Def",
          "Gender": "Fem",
          "Number": "Sing",
          "PronType": "Art"
        },
        "lemma": "der",
        "shape": "xxx",
        "tag": "ART",
        "lang": "de",
        "prefix": "d",
        "suffix": "die"
      },
      {
        "text": "Geschichte",
        "pos": "NOUN",
        "dep": "sb",
        "morph": {
          "Case": "Nom",
          "Gender": "Fem",
          "Number": "Sing"
        },
        "lemma": "Geschichte",
        "shape": "Xxxxx",
        "tag": "NN",
        "lang": "de",
        "prefix": "G",
        "suffix": "hte"
      }
    ],
    [
      {
        "text": "elf",
        "pos": "NUM",
        "dep": "nk",
        "morph": {},
        "lemma": "elf",
        "shape": "xxx",
        "tag": "CARD",
        "lang": "de",
        "prefix": "e",
        "suffix": "elf"
      },
      {
        "text": "Uhr",
        "pos": "NOUN",
        "dep": "pd",
        "morph": {
          "Gender": "Fem"
        },
        "lemma": "Uhr",
        "shape": "Xxx",
        "tag": "NN",
        "lang": "de",
        "prefix": "U",
        "suffix": "Uhr"
      }
    ],
    [
      {
        "text": "dem",
        "pos": "DET",
        "dep": "nk",
        "morph": {
          "Case": "Dat",
          "Definite": "Def",
          "Gender": "Masc",
          "Number": "Sing",
          "PronType": "Art"
        },
        "lemma": "der",
        "shape": "xxx",
        "tag": "ART",
        "lang": "de",
        "prefix": "d",
        "suffix": "dem"
      },
      {
        "text": "Aufzug",
        "pos": "NOUN",
        "dep": "nk",
        "morph": {
          "Case": "Dat",
          "Gender": "Masc",
          "Number": "Sing"
        },
        "lemma": "Aufzug",
        "shape": "Xxxxx",
        "tag": "NN",
        "lang": "de",
        "prefix": "A",
        "suffix": "zug"
      }
    ],
    [
      {
        "text": "der",
        "pos": "DET",
        "dep": "nk",
        "morph": {
          "Case": "Dat",
          "Definite": "Def",
          "Gender": "Fem",
          "Number": "Sing",
          "PronType": "Art"
        },
        "lemma": "der",
        "shape": "xxx",
        "tag": "ART",
        "lang": "de",
        "prefix": "d",
        "suffix": "der"
      },
      {
        "text": "U-Bahn",
        "pos": "NOUN",
        "dep": "nk",
        "morph": {
          "Case": "Dat",
          "Gender": "Fem",
          "Number": "Sing"
        },
        "lemma": "U-Bahn",
        "shape": "X-Xxxx",
        "tag": "NN",
        "lang": "de",
        "prefix": "U",
        "suffix": "ahn"
      }
    ],
    [
      {
        "text": "der",
        "pos": "DET",
        "dep": "nk",
        "morph": {
          "Case": "Nom",
          "Definite": "Def",
          "Gender": "Masc",
          "Number": "Sing",
          "PronType": "Art"
        },
        "lemma": "der",
        "shape": "xxx",
        "tag": "ART",
        "lang": "de",
        "prefix": "d",
        "suffix": "der"
      },
      {
        "text": "Flughafen",
        "pos": "NOUN",
        "dep": "sb",
        "morph": {
          "Case": "Nom",
          "Gender": "Masc",
          "Number": "Sing"
        },
        "lemma": "Flughafen",
        "shape": "Xxxxx",
        "tag": "NN",
        "lang": "de",
        "prefix": "F",
        "suffix": "fen"
      }
    ],
    [
      {
        "text": "das",
        "pos": "DET",
        "dep": "nk",
        "morph": {
          "Case": "Acc",
          "Definite": "Def",
          "Gender": "Neut",
          "Number": "Sing",
          "PronType": "Art"
        },
        "lemma": "der",
        "shape": "xxx",
        "tag": "ART",
        "lang": "de",
        "prefix": "d",
        "suffix": "das"
      },
      {
        "text": "Flughafengeb\u00e4ude",
        "pos": "NOUN",
        "dep": "nk",
        "morph": {
          "Case": "Acc",
          "Gender": "Neut",
          "Number": "Sing"
        },
        "lemma": "Flughafengeb\u00e4ude",
        "shape": "Xxxxx",
        "tag": "NN",
        "lang": "de",
        "prefix": "F",
        "suffix": "ude"
      }
    ],
    [
      {
        "text": "unserem",
        "pos": "DET",
        "dep": "nk",
        "morph": {
          "Case": "Dat",
          "Gender": "Neut",
          "Number": "Sing",
          "Poss": "Yes",
          "PronType": "Prs"
        },
        "lemma": "unser",
        "shape": "xxxx",
        "tag": "PPOSAT",
        "lang": "de",
        "prefix": "u",
        "suffix": "rem"
      },
      {
        "text": "Gate",
        "pos": "NOUN",
        "dep": "nk",
        "morph": {
          "Case": "Dat",
          "Gender": "Neut",
          "Number": "Sing"
        },
        "lemma": "Gate",
        "shape": "Xxxx",
        "tag": "NN",
        "lang": "de",
        "prefix": "G",
        "suffix": "ate"
      }
    ],
    [
      {
        "text": "ein",
        "pos": "DET",
        "dep": "nk",
        "morph": {
          "Case": "Acc",
          "Definite": "Ind",
          "Gender": "Neut",
          "Number": "Sing",
          "PronType": "Art"
        },
        "lemma": "ein",
        "shape": "xxx",
        "tag": "ART",
        "lang": "de",
        "prefix": "e",
        "suffix": "ein"
      },
      {
        "text": "Flugzeug",
        "pos": "NOUN",
        "dep": "nk",
        "morph": {
          "Case": "Acc",
          "Gender": "Neut",
          "Number": "Sing"
        },
        "lemma": "Flugzeug",
        "shape": "Xxxxx",
        "tag": "NN",
        "lang": "de",
        "prefix": "F",
        "suffix": "eug"
      }
    ],
    [
      {
        "text": "ein",
        "pos": "DET",
        "dep": "nk",
        "morph": {
          "Case": "Nom",
          "Definite": "Ind",
          "Gender": "Masc",
          "Number": "Sing",
          "PronType": "Art"
        },
        "lemma": "ein",
        "shape": "xxx",
        "tag": "ART",
        "lang": "de",
        "prefix": "e",
        "suffix": "ein"
      },
      {
        "text": "Unfall",
        "pos": "NOUN",
        "dep": "sb",
        "morph": {
          "Case": "Nom",
          "Gender": "Masc",
          "Number": "Sing"
        },
        "lemma": "Unfall",
        "shape": "Xxxxx",
        "tag": "NN",
        "lang": "de",
        "prefix": "U",
        "suffix": "all"
      }
    ],
    [
      {
        "text": "einem",
        "pos": "DET",
        "dep": "nk",
        "morph": {
          "Case": "Dat",
          "Definite": "Ind",
          "Gender": "Masc",
          "Number": "Sing",
          "PronType": "Art"
        },
        "lemma": "ein",
        "shape": "xxxx",
        "tag": "ART",
        "lang": "de",
        "prefix": "e",
        "suffix": "nem"
      },
      {
        "text": "Unfall",
        "pos": "NOUN",
        "dep": "nk",
        "morph": {
          "Case": "Dat",
          "Gender": "Masc",
          "Number": "Sing"
        },
        "lemma": "Unfall",
        "shape": "Xxxxx",
        "tag": "NN",
        "lang": "de",
        "prefix": "U",
        "suffix": "all"
      }
    ],
    [
      {
        "text": "meinen",
        "pos": "DET",
        "dep": "nk",
        "morph": {
          "Case": "Acc",
          "Gender": "Masc",
          "Number": "Sing",
          "Poss": "Yes",
          "PronType": "Prs"
        },
        "lemma": "mein",
        "shape": "xxxx",
        "tag": "PPOSAT",
        "lang": "de",
        "prefix": "m",
        "suffix": "nen"
      },
      {
        "text": "Pass",
        "pos": "NOUN",
        "dep": "oa",
        "morph": {
          "Case": "Acc",
          "Gender": "Masc",
          "Number": "Sing"
        },
        "lemma": "Pass",
        "shape": "Xxxx",
        "tag": "NN",
        "lang": "de",
        "prefix": "P",
        "suffix": "ass"
      }
    ],
    [
      {
        "text": "meinen",
        "pos": "DET",
        "dep": "nk",
        "morph": {
          "Case": "Acc",
          "Gender": "Masc",
          "Number": "Sing",
          "Poss": "Yes",
          "PronType": "Prs"
        },
        "lemma": "mein",
        "shape": "xxxx",
        "tag": "PPOSAT",
        "lang": "de",
        "prefix": "m",
        "suffix": "nen"
      },
      {
        "text": "Pass",
        "pos": "NOUN",
        "dep": "oa",
        "morph": {
          "Case": "Acc",
          "Gender": "Masc",
          "Number": "Sing"
        },
        "lemma": "Pass",
        "shape": "Xxxx",
        "tag": "NN",
        "lang": "de",
        "prefix": "P",
        "suffix": "ass"
      }
    ],
    [
      {
        "text": "unsere",
        "pos": "DET",
        "dep": "nk",
        "morph": {
          "Case": "Acc",
          "Gender": "Fem",
          "Number": "Plur",
          "Poss": "Yes",
          "PronType": "Prs"
        },
        "lemma": "unser",
        "shape": "xxxx",
        "tag": "PPOSAT",
        "lang": "de",
        "prefix": "u",
        "suffix": "ere"
      },
      {
        "text": "Klamotten",
        "pos": "NOUN",
        "dep": "oa",
        "morph": {
          "Case": "Acc",
          "Gender": "Fem",
          "Number": "Plur"
        },
        "lemma": "Klamotte",
        "shape": "Xxxxx",
        "tag": "NN",
        "lang": "de",
        "prefix": "K",
        "suffix": "ten"
      }
    ],
    [
      {
        "text": "die",
        "pos": "DET",
        "dep": "nk",
        "morph": {
          "Case": "Nom",
          "Definite": "Def",
          "Gender": "Fem",
          "Number": "Sing",
          "PronType": "Art"
        },
        "lemma": "der",
        "shape": "xxx",
        "tag": "ART",
        "lang": "de",
        "prefix": "d",
        "suffix": "die"
      },
      {
        "text": "Polizei",
        "pos": "NOUN",
        "dep": "sb",
        "morph": {
          "Case": "Nom",
          "Gender": "Fem",
          "Number": "Sing"
        },
        "lemma": "Polizei",
        "shape": "Xxxxx",
        "tag": "NN",
        "lang": "de",
        "prefix": "P",
        "suffix": "zei"
      }
    ],
    [
      {
        "text": "meinen",
        "pos": "DET",
        "dep": "nk",
        "morph": {
          "Case": "Acc",
          "Gender": "Masc",
          "Number": "Sing",
          "Poss": "Yes",
          "PronType": "Prs"
        },
        "lemma": "mein",
        "shape": "xxxx",
        "tag": "PPOSAT",
        "lang": "de",
        "prefix": "m",
        "suffix": "nen"
      },
      {
        "text": "Pass",
        "pos": "NOUN",
        "dep": "oa",
        "morph": {
          "Case": "Acc",
          "Gender": "Masc",
          "Number": "Sing"
        },
        "lemma": "Pass",
        "shape": "Xxxx",
        "tag": "NN",
        "lang": "de",
        "prefix": "P",
        "suffix": "ass"
      }
    ],
    [
      {
        "text": "die",
        "pos": "DET",
        "dep": "nk",
        "morph": {
          "Case": "Acc",
          "Definite": "Def",
          "Gender": "Fem",
          "Number": "Sing",
          "PronType": "Art"
        },
        "lemma": "der",
        "shape": "xxx",
        "tag": "ART",
        "lang": "de",
        "prefix": "d",
        "suffix": "die"
      },
      {
        "text": "EASY",
        "pos": "PROPN",
        "dep": "nk",
        "morph": {},
        "lemma": "EASY",
        "shape": "XXXX",
        "tag": "NE",
        "lang": "de",
        "prefix": "E",
        "suffix": "ASY"
      },
      {
        "text": "German",
        "pos": "PROPN",
        "dep": "nk",
        "morph": {},
        "lemma": "German",
        "shape": "Xxxxx",
        "tag": "NE",
        "lang": "de",
        "prefix": "G",
        "suffix": "man"
      },
      {
        "text": "Tour",
        "pos": "NOUN",
        "dep": "oa",
        "morph": {
          "Case": "Acc",
          "Gender": "Fem",
          "Number": "Sing"
        },
        "lemma": "Tour",
        "shape": "Xxxx",
        "tag": "NN",
        "lang": "de",
        "prefix": "T",
        "suffix": "our"
      }
    ],
    [
      {
        "text": "einen",
        "pos": "DET",
        "dep": "nk",
        "morph": {
          "Case": "Acc",
          "Definite": "Ind",
          "Gender": "Masc",
          "Number": "Sing",
          "PronType": "Art"
        },
        "lemma": "ein",
        "shape": "xxxx",
        "tag": "ART",
        "lang": "de",
        "prefix": "e",
        "suffix": "nen"
      },
      {
        "text": "neuen",
        "pos": "ADJ",
        "dep": "nk",
        "morph": {
          "Case": "Acc",
          "Degree": "Pos",
          "Gender": "Masc",
          "Number": "Sing"
        },
        "lemma": "neu",
        "shape": "xxxx",
        "tag": "ADJA",
        "lang": "de",
        "prefix": "n",
        "suffix": "uen"
      },
      {
        "text": "Plan",
        "pos": "NOUN",
        "dep": "oa",
        "morph": {
          "Case": "Acc",
          "Gender": "Masc",
          "Number": "Sing"
        },
        "lemma": "Plan",
        "shape": "Xxxx",
        "tag": "NN",
        "lang": "de",
        "prefix": "P",
        "suffix": "lan"
      }
    ],
    [
      {
        "text": "n\u00e4chsten",
        "pos": "ADJ",
        "dep": "nk",
        "morph": {
          "Case": "Dat",
          "Degree": "Pos",
          "Gender": "Masc",
          "Number": "Sing"
        },
        "lemma": "n\u00e4chster",
        "shape": "xxxx",
        "tag": "ADJA",
        "lang": "de",
        "prefix": "n",
        "suffix": "ten"
      },
      {
        "text": "Tag",
        "pos": "NOUN",
        "dep": "nk",
        "morph": {
          "Case": "Dat",
          "Gender": "Masc",
          "Number": "Sing"
        },
        "lemma": "Tag",
        "shape": "Xxx",
        "tag": "NN",
        "lang": "de",
        "prefix": "T",
        "suffix": "Tag"
      }
    ],
    [
      {
        "text": "6",
        "pos": "NUM",
        "dep": "nk",
        "morph": {},
        "lemma": "6",
        "shape": "d",
        "tag": "CARD",
        "lang": "de",
        "prefix": "6",
        "suffix": "6"
      },
      {
        "text": "Uhr",
        "pos": "NOUN",
        "dep": "nk",
        "morph": {
          "Case": "Acc",
          "Gender": "Fem",
          "Number": "Sing"
        },
        "lemma": "Uhr",
        "shape": "Xxx",
        "tag": "NN",
        "lang": "de",
        "prefix": "U",
        "suffix": "Uhr"
      }
    ],
    [
      {
        "text": "20",
        "pos": "NUM",
        "dep": "nk",
        "morph": {},
        "lemma": "20",
        "shape": "dd",
        "tag": "CARD",
        "lang": "de",
        "prefix": "2",
        "suffix": "20"
      },
      {
        "text": "Minuten",
        "pos": "NOUN",
        "dep": "oa",
        "morph": {
          "Case": "Acc",
          "Gender": "Fem",
          "Number": "Plur"
        },
        "lemma": "Minute",
        "shape": "Xxxxx",
        "tag": "NN",
        "lang": "de",
        "prefix": "M",
        "suffix": "ten"
      }
    ],
    [
      {
        "text": "das",
        "pos": "DET",
        "dep": "nk",
        "morph": {
          "Case": "Nom",
          "Definite": "Def",
          "Gender": "Neut",
          "Number": "Sing",
          "PronType": "Art"
        },
        "lemma": "der",
        "shape": "xxx",
        "tag": "ART",
        "lang": "de",
        "prefix": "d",
        "suffix": "das"
      },
      {
        "text": "Flugzeug",
        "pos": "NOUN",
        "dep": "sb",
        "morph": {
          "Case": "Nom",
          "Gender": "Neut",
          "Number": "Sing"
        },
        "lemma": "Flugzeug",
        "shape": "Xxxxx",
        "tag": "NN",
        "lang": "de",
        "prefix": "F",
        "suffix": "eug"
      }
    ],
    [
      {
        "text": "Eine",
        "pos": "DET",
        "dep": "nk",
        "morph": {
          "Case": "Nom",
          "Definite": "Ind",
          "Gender": "Fem",
          "Number": "Sing",
          "PronType": "Art"
        },
        "lemma": "ein",
        "shape": "Xxxx",
        "tag": "ART",
        "lang": "de",
        "prefix": "E",
        "suffix": "ine"
      },
      {
        "text": "Frau",
        "pos": "NOUN",
        "dep": "sb",
        "morph": {
          "Case": "Nom",
          "Gender": "Fem",
          "Number": "Sing"
        },
        "lemma": "Frau",
        "shape": "Xxxx",
        "tag": "NN",
        "lang": "de",
        "prefix": "F",
        "suffix": "rau"
      }
    ],
    [
      {
        "text": "Diese",
        "pos": "DET",
        "dep": "nk",
        "morph": {
          "Case": "Nom",
          "Gender": "Fem",
          "Number": "Sing",
          "PronType": "Dem"
        },
        "lemma": "dieser",
        "shape": "Xxxxx",
        "tag": "PDAT",
        "lang": "de",
        "prefix": "D",
        "suffix": "ese"
      },
      {
        "text": "Frau",
        "pos": "NOUN",
        "dep": "sb",
        "morph": {
          "Case": "Nom",
          "Gender": "Fem",
          "Number": "Sing"
        },
        "lemma": "Frau",
        "shape": "Xxxx",
        "tag": "NN",
        "lang": "de",
        "prefix": "F",
        "suffix": "rau"
      }
    ],
    [
      {
        "text": "meinen",
        "pos": "DET",
        "dep": "nk",
        "morph": {
          "Case": "Acc",
          "Gender": "Masc",
          "Number": "Sing",
          "Poss": "Yes",
          "PronType": "Prs"
        },
        "lemma": "mein",
        "shape": "xxxx",
        "tag": "PPOSAT",
        "lang": "de",
        "prefix": "m",
        "suffix": "nen"
      },
      {
        "text": "Pass",
        "pos": "NOUN",
        "dep": "oa",
        "morph": {
          "Case": "Acc",
          "Gender": "Masc",
          "Number": "Sing"
        },
        "lemma": "Pass",
        "shape": "Xxxx",
        "tag": "NN",
        "lang": "de",
        "prefix": "P",
        "suffix": "ass"
      }
    ],
    [
      {
        "text": "vier",
        "pos": "NUM",
        "dep": "nk",
        "morph": {},
        "lemma": "vier",
        "shape": "xxxx",
        "tag": "CARD",
        "lang": "de",
        "prefix": "v",
        "suffix": "ier"
      },
      {
        "text": "Stunden",
        "pos": "NOUN",
        "dep": "nk",
        "morph": {
          "Case": "Dat",
          "Gender": "Fem",
          "Number": "Plur"
        },
        "lemma": "Stunde",
        "shape": "Xxxxx",
        "tag": "NN",
        "lang": "de",
        "prefix": "S",
        "suffix": "den"
      }
    ],
    [
      {
        "text": "dann",
        "pos": "ADV",
        "dep": "mo",
        "morph": {},
        "lemma": "dann",
        "shape": "xxxx",
        "tag": "ADV",
        "lang": "de",
        "prefix": "d",
        "suffix": "ann"
      },
      {
        "text": "direkt",
        "pos": "ADV",
        "dep": "mo",
        "morph": {
          "Degree": "Pos"
        },
        "lemma": "direkt",
        "shape": "xxxx",
        "tag": "ADJD",
        "lang": "de",
        "prefix": "d",
        "suffix": "ekt"
      },
      {
        "text": "wieder",
        "pos": "ADV",
        "dep": "mo",
        "morph": {},
        "lemma": "wieder",
        "shape": "xxxx",
        "tag": "ADV",
        "lang": "de",
        "prefix": "w",
        "suffix": "der"
      },
      {
        "text": "vier",
        "pos": "NUM",
        "dep": "nk",
        "morph": {},
        "lemma": "vier",
        "shape": "xxxx",
        "tag": "CARD",
        "lang": "de",
        "prefix": "v",
        "suffix": "ier"
      },
      {
        "text": "Stunden",
        "pos": "NOUN",
        "dep": "cj",
        "morph": {
          "Case": "Acc",
          "Gender": "Fem",
          "Number": "Plur"
        },
        "lemma": "Stunde",
        "shape": "Xxxxx",
        "tag": "NN",
        "lang": "de",
        "prefix": "S",
        "suffix": "den"
      }
    ],
    [
      {
        "text": "die",
        "pos": "DET",
        "dep": "nk",
        "morph": {
          "Case": "Nom",
          "Definite": "Def",
          "Gender": "Fem",
          "Number": "Sing",
          "PronType": "Art"
        },
        "lemma": "der",
        "shape": "xxx",
        "tag": "ART",
        "lang": "de",
        "prefix": "d",
        "suffix": "die"
      },
      {
        "text": "lokale",
        "pos": "ADJ",
        "dep": "nk",
        "morph": {
          "Case": "Nom",
          "Degree": "Pos",
          "Gender": "Fem",
          "Number": "Sing"
        },
        "lemma": "lokal",
        "shape": "xxxx",
        "tag": "ADJA",
        "lang": "de",
        "prefix": "l",
        "suffix": "ale"
      },
      {
        "text": "Zeit",
        "pos": "NOUN",
        "dep": "sb",
        "morph": {
          "Case": "Nom",
          "Gender": "Fem",
          "Number": "Sing"
        },
        "lemma": "Zeit",
        "shape": "Xxxx",
        "tag": "NN",
        "lang": "de",
        "prefix": "Z",
        "suffix": "eit"
      }
    ],
    [
      {
        "text": "zwei",
        "pos": "NUM",
        "dep": "nk",
        "morph": {},
        "lemma": "zwei",
        "shape": "xxxx",
        "tag": "CARD",
        "lang": "de",
        "prefix": "z",
        "suffix": "wei"
      },
      {
        "text": "Uhr",
        "pos": "NOUN",
        "dep": "nk",
        "morph": {
          "Case": "Acc",
          "Gender": "Fem",
          "Number": "Sing"
        },
        "lemma": "Uhr",
        "shape": "Xxx",
        "tag": "NN",
        "lang": "de",
        "prefix": "U",
        "suffix": "Uhr"
      }
    ],
    [
      {
        "text": "unserem",
        "pos": "DET",
        "dep": "nk",
        "morph": {
          "Case": "Dat",
          "Gender": "Neut",
          "Number": "Sing",
          "Poss": "Yes",
          "PronType": "Prs"
        },
        "lemma": "unser",
        "shape": "xxxx",
        "tag": "PPOSAT",
        "lang": "de",
        "prefix": "u",
        "suffix": "rem"
      },
      {
        "text": "Gate",
        "pos": "NOUN",
        "dep": "nk",
        "morph": {
          "Case": "Dat",
          "Gender": "Neut",
          "Number": "Sing"
        },
        "lemma": "Gate",
        "shape": "Xxxx",
        "tag": "NN",
        "lang": "de",
        "prefix": "G",
        "suffix": "ate"
      }
    ],
    [
      {
        "text": "Sieben",
        "pos": "NUM",
        "dep": "nk",
        "morph": {},
        "lemma": "sieben",
        "shape": "Xxxxx",
        "tag": "CARD",
        "lang": "de",
        "prefix": "S",
        "suffix": "ben"
      },
      {
        "text": "Stunden",
        "pos": "NOUN",
        "dep": "ams",
        "morph": {
          "Case": "Acc",
          "Gender": "Fem",
          "Number": "Plur"
        },
        "lemma": "Stunde",
        "shape": "Xxxxx",
        "tag": "NN",
        "lang": "de",
        "prefix": "S",
        "suffix": "den"
      }
    ],
    [
      {
        "text": "dem",
        "pos": "DET",
        "dep": "nk",
        "morph": {
          "Case": "Dat",
          "Definite": "Def",
          "Gender": "Masc",
          "Number": "Sing",
          "PronType": "Art"
        },
        "lemma": "der",
        "shape": "xxx",
        "tag": "ART",
        "lang": "de",
        "prefix": "d",
        "suffix": "dem"
      },
      {
        "text": "Zug",
        "pos": "NOUN",
        "dep": "nk",
        "morph": {
          "Case": "Dat",
          "Gender": "Masc",
          "Number": "Sing"
        },
        "lemma": "Zug",
        "shape": "Xxx",
        "tag": "NN",
        "lang": "de",
        "prefix": "Z",
        "suffix": "Zug"
      }
    ],
    [
      {
        "text": "die",
        "pos": "DET",
        "dep": "nk",
        "morph": {
          "Case": "Acc",
          "Definite": "Def",
          "Gender": "Fem",
          "Number": "Sing",
          "PronType": "Art"
        },
        "lemma": "der",
        "shape": "xxx",
        "tag": "ART",
        "lang": "de",
        "prefix": "d",
        "suffix": "die"
      },
      {
        "text": "Stadt",
        "pos": "NOUN",
        "dep": "nk",
        "morph": {
          "Case": "Acc",
          "Gender": "Fem",
          "Number": "Sing"
        },
        "lemma": "Stadt",
        "shape": "Xxxxx",
        "tag": "NN",
        "lang": "de",
        "prefix": "S",
        "suffix": "adt"
      }
    ],
    [
      {
        "text": "der",
        "pos": "DET",
        "dep": "nk",
        "morph": {
          "Case": "Dat",
          "Definite": "Def",
          "Gender": "Fem",
          "Number": "Sing",
          "PronType": "Art"
        },
        "lemma": "der",
        "shape": "xxx",
        "tag": "ART",
        "lang": "de",
        "prefix": "d",
        "suffix": "der"
      },
      {
        "text": "Bahnstation",
        "pos": "NOUN",
        "dep": "nk",
        "morph": {
          "Case": "Dat",
          "Gender": "Fem",
          "Number": "Sing"
        },
        "lemma": "Bahnstation",
        "shape": "Xxxxx",
        "tag": "NN",
        "lang": "de",
        "prefix": "B",
        "suffix": "ion"
      }
    ],
    [
      {
        "text": "der",
        "pos": "DET",
        "dep": "nk",
        "morph": {
          "Case": "Dat",
          "Definite": "Def",
          "Gender": "Fem",
          "Number": "Sing",
          "PronType": "Art"
        },
        "lemma": "der",
        "shape": "xxx",
        "tag": "ART",
        "lang": "de",
        "prefix": "d",
        "suffix": "der"
      },
      {
        "text": "Bahnstation",
        "pos": "NOUN",
        "dep": "nk",
        "morph": {
          "Case": "Dat",
          "Gender": "Fem",
          "Number": "Sing"
        },
        "lemma": "Bahnstation",
        "shape": "Xxxxx",
        "tag": "NN",
        "lang": "de",
        "prefix": "B",
        "suffix": "ion"
      }
    ],
    [
      {
        "text": "unserer",
        "pos": "DET",
        "dep": "nk",
        "morph": {
          "Case": "Dat",
          "Gender": "Fem",
          "Number": "Sing",
          "Poss": "Yes",
          "PronType": "Prs"
        },
        "lemma": "unser",
        "shape": "xxxx",
        "tag": "PPOSAT",
        "lang": "de",
        "prefix": "u",
        "suffix": "rer"
      },
      {
        "text": "Wohnung",
        "pos": "NOUN",
        "dep": "nk",
        "morph": {
          "Case": "Dat",
          "Gender": "Fem",
          "Number": "Sing"
        },
        "lemma": "Wohnung",
        "shape": "Xxxxx",
        "tag": "NN",
        "lang": "de",
        "prefix": "W",
        "suffix": "ung"
      }
    ],
    [
      {
        "text": "40",
        "pos": "NUM",
        "dep": "nk",
        "morph": {},
        "lemma": "40",
        "shape": "dd",
        "tag": "CARD",
        "lang": "de",
        "prefix": "4",
        "suffix": "40"
      },
      {
        "text": "Stunden",
        "pos": "NOUN",
        "dep": "nk",
        "morph": {
          "Case": "Dat",
          "Gender": "Fem",
          "Number": "Plur"
        },
        "lemma": "Stunde",
        "shape": "Xxxxx",
        "tag": "NN",
        "lang": "de",
        "prefix": "S",
        "suffix": "den"
      }
    ],
    [
      {
        "text": "diese",
        "pos": "DET",
        "dep": "nk",
        "morph": {
          "Case": "Acc",
          "Gender": "Fem",
          "Number": "Plur",
          "PronType": "Dem"
        },
        "lemma": "dieser",
        "shape": "xxxx",
        "tag": "PDAT",
        "lang": "de",
        "prefix": "d",
        "suffix": "ese"
      },
      {
        "text": "Pr\u00e4positionen",
        "pos": "NOUN",
        "dep": "oa",
        "morph": {
          "Case": "Acc",
          "Gender": "Fem",
          "Number": "Plur"
        },
        "lemma": "Pr\u00e4position",
        "shape": "Xxxxx",
        "tag": "NN",
        "lang": "de",
        "prefix": "P",
        "suffix": "nen"
      }
    ],
    [
      {
        "text": "ein",
        "pos": "DET",
        "dep": "nk",
        "morph": {
          "Case": "Nom",
          "Definite": "Ind",
          "Gender": "Masc",
          "Number": "Sing",
          "PronType": "Art"
        },
        "lemma": "ein",
        "shape": "xxx",
        "tag": "ART",
        "lang": "de",
        "prefix": "e",
        "suffix": "ein"
      },
      {
        "text": "Patron",
        "pos": "NOUN",
        "dep": "pd",
        "morph": {
          "Case": "Nom",
          "Gender": "Masc",
          "Number": "Sing"
        },
        "lemma": "Patron",
        "shape": "Xxxxx",
        "tag": "NN",
        "lang": "de",
        "prefix": "P",
        "suffix": "ron"
      }
    ],
    [
      {
        "text": "jede",
        "pos": "DET",
        "dep": "nk",
        "morph": {
          "Case": "Acc",
          "Gender": "Fem",
          "Number": "Sing",
          "PronType": "Ind"
        },
        "lemma": "jeder",
        "shape": "xxxx",
        "tag": "PIAT",
        "lang": "de",
        "prefix": "j",
        "suffix": "ede"
      },
      {
        "text": "Woche",
        "pos": "NOUN",
        "dep": "mo",
        "morph": {
          "Case": "Acc",
          "Gender": "Fem",
          "Number": "Sing"
        },
        "lemma": "Woche",
        "shape": "Xxxxx",
        "tag": "NN",
        "lang": "de",
        "prefix": "W",
        "suffix": "che"
      }
    ],
    [
      {
        "text": "interaktive",
        "pos": "ADJ",
        "dep": "nk",
        "morph": {
          "Case": "Acc",
          "Degree": "Pos",
          "Gender": "Fem",
          "Number": "Plur"
        },
        "lemma": "interaktiv",
        "shape": "xxxx",
        "tag": "ADJA",
        "lang": "de",
        "prefix": "i",
        "suffix": "ive"
      },
      {
        "text": "\u00dcbungen",
        "pos": "NOUN",
        "dep": "oa",
        "morph": {
          "Case": "Acc",
          "Gender": "Fem",
          "Number": "Plur"
        },
        "lemma": "\u00dcbung",
        "shape": "Xxxxx",
        "tag": "NN",
        "lang": "de",
        "prefix": "\u00dc",
        "suffix": "gen"
      }
    ],
    [
      {
        "text": "diesem",
        "pos": "DET",
        "dep": "nk",
        "morph": {
          "Case": "Dat",
          "Gender": "Neut",
          "Number": "Sing",
          "PronType": "Dem"
        },
        "lemma": "dieser",
        "shape": "xxxx",
        "tag": "PDAT",
        "lang": "de",
        "prefix": "d",
        "suffix": "sem"
      },
      {
        "text": "Thema",
        "pos": "NOUN",
        "dep": "nk",
        "morph": {
          "Case": "Dat",
          "Gender": "Neut",
          "Number": "Sing"
        },
        "lemma": "Thema",
        "shape": "Xxxxx",
        "tag": "NN",
        "lang": "de",
        "prefix": "T",
        "suffix": "ema"
      }
    ],
    [
      {
        "text": "ein",
        "pos": "DET",
        "dep": "nk",
        "morph": {
          "Case": "Acc",
          "Definite": "Ind",
          "Gender": "Neut",
          "Number": "Sing",
          "PronType": "Art"
        },
        "lemma": "ein",
        "shape": "xxx",
        "tag": "ART",
        "lang": "de",
        "prefix": "e",
        "suffix": "ein"
      },
      {
        "text": "eigenes",
        "pos": "ADJ",
        "dep": "nk",
        "morph": {
          "Case": "Acc",
          "Degree": "Pos",
          "Gender": "Neut",
          "Number": "Sing"
        },
        "lemma": "eigen",
        "shape": "xxxx",
        "tag": "ADJA",
        "lang": "de",
        "prefix": "e",
        "suffix": "nes"
      },
      {
        "text": "\u00dcbungsblatt",
        "pos": "NOUN",
        "dep": "oa",
        "morph": {
          "Case": "Acc",
          "Gender": "Neut",
          "Number": "Sing"
        },
        "lemma": "\u00dcbungsblatt",
        "shape": "Xxxxx",
        "tag": "NN",
        "lang": "de",
        "prefix": "\u00dc",
        "suffix": "att"
      }
    ],
    [
      {
        "text": "dem",
        "pos": "DET",
        "dep": "nk",
        "morph": {
          "Case": "Dat",
          "Definite": "Def",
          "Gender": "Masc",
          "Number": "Sing",
          "PronType": "Art"
        },
        "lemma": "der",
        "shape": "xxx",
        "tag": "ART",
        "lang": "de",
        "prefix": "d",
        "suffix": "dem"
      },
      {
        "text": "Weg",
        "pos": "NOUN",
        "dep": "nk",
        "morph": {
          "Case": "Dat",
          "Gender": "Masc",
          "Number": "Sing"
        },
        "lemma": "Weg",
        "shape": "Xxx",
        "tag": "NN",
        "lang": "de",
        "prefix": "W",
        "suffix": "Weg"
      }
    ],
    [
      {
        "text": "unsere",
        "pos": "DET",
        "dep": "nk",
        "morph": {
          "Case": "Nom",
          "Gender": "Fem",
          "Number": "Sing",
          "Poss": "Yes",
          "PronType": "Prs"
        },
        "lemma": "unser",
        "shape": "xxxx",
        "tag": "PPOSAT",
        "lang": "de",
        "prefix": "u",
        "suffix": "ere"
      },
      {
        "text": "EasyGerman-Tour",
        "pos": "NOUN",
        "dep": "sb",
        "morph": {
          "Case": "Nom",
          "Gender": "Fem",
          "Number": "Sing"
        },
        "lemma": "EasyGerman-Tour",
        "shape": "XxxxXxxxx-Xxxx",
        "tag": "NN",
        "lang": "de",
        "prefix": "E",
        "suffix": "our"
      }
    ],
    [
      {
        "text": "Die",
        "pos": "DET",
        "dep": "nk",
        "morph": {
          "Case": "Nom",
          "Definite": "Def",
          "Number": "Plur",
          "PronType": "Art"
        },
        "lemma": "der",
        "shape": "Xxx",
        "tag": "ART",
        "lang": "de",
        "prefix": "D",
        "suffix": "Die"
      },
      {
        "text": "Links",
        "pos": "NOUN",
        "dep": "sb",
        "morph": {
          "Case": "Nom",
          "Number": "Plur"
        },
        "lemma": "links",
        "shape": "Xxxxx",
        "tag": "NN",
        "lang": "de",
        "prefix": "L",
        "suffix": "nks"
      }
    ],
    [
      {
        "text": "n\u00e4chste",
        "pos": "ADJ",
        "dep": "nk",
        "morph": {
          "Case": "Acc",
          "Degree": "Pos",
          "Gender": "Fem",
          "Number": "Sing"
        },
        "lemma": "n\u00e4chster",
        "shape": "xxxx",
        "tag": "ADJA",
        "lang": "de",
        "prefix": "n",
        "suffix": "ste"
      },
      {
        "text": "Woche",
        "pos": "NOUN",
        "dep": "nk",
        "morph": {
          "Case": "Acc",
          "Gender": "Fem",
          "Number": "Sing"
        },
        "lemma": "Woche",
        "shape": "Xxxxx",
        "tag": "NN",
        "lang": "de",
        "prefix": "W",
        "suffix": "che"
      }
    ]
  ]
}